cores/__init__.py
cores/const/__const.py
cores/const/__init__.py
cores/const/api/__init__.py
cores/const/api/api.py
cores/const/api/request.py
cores/const/api/swagger.py
cores/const/common/__init__.py
cores/const/common/color_const.py
cores/const/common/common_const.py
cores/const/common/emoji_const.py
cores/const/common/environment_const.py
cores/const/common/key_codes_const.py
cores/const/common/msg_const.py
cores/const/common/path_const.py
cores/const/common/store_const.py
cores/const/common/string_const.py
cores/const/common/times_const.py
cores/const/common/types_const.py
cores/const/config/__init__.py
cores/const/config/testlink_const.py
cores/const/custom_exception/__init__.py
cores/const/custom_exception/custom_exception.py
cores/const/database/__init__.py
cores/const/database/db_const.py
cores/const/mobile/__init__.py
cores/const/mobile/appium_server_const.py
cores/const/mobile/capabilities_const.py
cores/const/mobile/command_const.py
cores/const/mobile/device_const.py
cores/const/mobile/mobile_command_const.py
cores/const/web/__init__.py
cores/const/web/browsers_const.py
cores/decorators/__init__.py
cores/decorators/handle_exception.py
cores/decorators/parse_config.py
cores/decorators/retry.py
cores/factory/__init__.py
cores/factory/database_factory/__init__.py
cores/factory/database_factory/database_conn_generator.py
cores/factory/database_factory/database_factory.py
cores/factory/driver_factory/__init__.py
cores/factory/driver_factory/appium/__init__.py
cores/factory/driver_factory/appium/appium_actions.py
cores/factory/driver_factory/appium/appium_server.py
cores/factory/driver_factory/appium/application_helper.py
cores/factory/driver_factory/appium/mobile_driver.py
cores/factory/driver_factory/appium/virtual_device.py
cores/factory/driver_factory/selenium/__init__.py
cores/factory/driver_factory/selenium/locator_modify_util.py
cores/factory/driver_factory/selenium/selenium_actions.py
cores/factory/driver_factory/selenium/selenium_base.py
dale_core_platform-0.3.dist-info/LICENSE
dale_core_platform-0.3.dist-info/METADATA
dale_core_platform-0.3.dist-info/WHEEL
dale_core_platform-0.3.dist-info/top_level.txt
dale_core_platform-0.3.dist-info/RECORD
